mseep_terraform_cloud_mcp-0.8.12.dist-info/licenses/LICENSE
terraform_cloud_mcp/__init__.py
terraform_cloud_mcp/server.py
terraform_cloud_mcp/api/__init__.py
terraform_cloud_mcp/api/client.py
terraform_cloud_mcp/models/__init__.py
terraform_cloud_mcp/models/account.py
terraform_cloud_mcp/models/applies.py
terraform_cloud_mcp/models/assessment_results.py
terraform_cloud_mcp/models/base.py
terraform_cloud_mcp/models/cost_estimates.py
terraform_cloud_mcp/models/organizations.py
terraform_cloud_mcp/models/plans.py
terraform_cloud_mcp/models/projects.py
terraform_cloud_mcp/models/runs.py
terraform_cloud_mcp/models/workspaces.py
terraform_cloud_mcp/tools/__init__.py
terraform_cloud_mcp/tools/account.py
terraform_cloud_mcp/tools/applies.py
terraform_cloud_mcp/tools/assessment_results.py
terraform_cloud_mcp/tools/cost_estimates.py
terraform_cloud_mcp/tools/organizations.py
terraform_cloud_mcp/tools/plans.py
terraform_cloud_mcp/tools/projects.py
terraform_cloud_mcp/tools/runs.py
terraform_cloud_mcp/tools/workspaces.py
terraform_cloud_mcp/utils/__init__.py
terraform_cloud_mcp/utils/decorators.py
terraform_cloud_mcp/utils/payload.py
terraform_cloud_mcp/utils/request.py
mseep_terraform_cloud_mcp-0.8.12.dist-info/METADATA
mseep_terraform_cloud_mcp-0.8.12.dist-info/WHEEL
mseep_terraform_cloud_mcp-0.8.12.dist-info/top_level.txt
mseep_terraform_cloud_mcp-0.8.12.dist-info/RECORD
